README
setup.py
pyatmlab/__init__.py
pyatmlab/collocations.py
pyatmlab/config.py
pyatmlab/constants.py
pyatmlab/dataset.py
pyatmlab/db.py
pyatmlab/geo.py
pyatmlab/graphics.py
pyatmlab/instruments.py
pyatmlab/io.py
pyatmlab/math.py
pyatmlab/meta.py
pyatmlab/physics.py
pyatmlab/stats.py
pyatmlab/time.py
pyatmlab/tools.py
pyatmlab/units.py
pyatmlab.egg-info/PKG-INFO
pyatmlab.egg-info/SOURCES.txt
pyatmlab.egg-info/dependency_links.txt
pyatmlab.egg-info/requires.txt
pyatmlab.egg-info/top_level.txt
pyatmlab/arts/__init__.py
pyatmlab/arts/_handlers.py
pyatmlab/arts/xml.py
pyatmlab/datasets/__init__.py
pyatmlab/datasets/_tovs_defs.py
pyatmlab/datasets/acefts.py
pyatmlab/datasets/foo.py
pyatmlab/datasets/groundbased.py
pyatmlab/datasets/tanso.py
pyatmlab/datasets/tovs.py
tests/__init__.py