Metadata-Version: 1.1
Name: pyatmlab
Version: 0.1.2
Summary: Diverse collection of tools for working with atmospheric data from remote sensing, modelling, and related applications.
Home-page: http://packages.python.org/pyatmlab
Author: Gerrit Holl
Author-email: g.holl@reading.ac.uk
License: Modified BSD License
Keywords: atmosphere,satellite,remote sensing,radiative transfer
Platform: UNKNOWN
Classifier: Development Status :: 3 - Alpha
Classifier: Intended Audience :: Science/Research
Classifier: License :: OSI Approved :: BSD License
Classifier: Programming Language :: Python :: 3.5
Classifier: Topic :: Scientific/Engineering :: Atmospheric Science
